batch/compile_prenight_metadata_cache.sh
batch/run_prenight_sims.sh
ci/Jenkinsfile_rubin_scheduler.conda
docs/Makefile
docs/api.rst
docs/archive.rst
docs/conf.py
docs/data-api.rst
docs/data-download.rst
docs/documenteer.toml
docs/fbs-api-basis-functions.rst
docs/fbs-api-detailers.rst
docs/fbs-api-example-scheduler.rst
docs/fbs-api-features.rst
docs/fbs-api-model-observatory.rst
docs/fbs-api-schedulers.rst
docs/fbs-api-sim-runner.rst
docs/fbs-api-surveys.rst
docs/fbs-api-utils.rst
docs/fbs-api.rst
docs/fbs-arch.rst
docs/fbs-output-schema.rst
docs/fbs-running.rst
docs/fbs.rst
docs/index.rst
docs/installation.rst
docs/introduction.rst
docs/sim-archive-api.rst
docs/site-models-api.rst
docs/site-models.rst
docs/skybrightness-pre-api.rst
docs/skybrightness-pre.rst
docs/user-guide.rst
docs/utils-api.rst
docs/utils.rst
rubin_scheduler/__init__.py
rubin_scheduler/version.py
rubin_scheduler/data/__init__.py
rubin_scheduler/data/data_sets.py
rubin_scheduler/data/rs_download_sky.py
rubin_scheduler/data/scheduler_download_data.py
rubin_scheduler/scheduler/__init__.py
rubin_scheduler/scheduler/sim_runner.py
rubin_scheduler/scheduler/basis_functions/__init__.py
rubin_scheduler/scheduler/basis_functions/basis_functions.py
rubin_scheduler/scheduler/basis_functions/feasibility_funcs.py
rubin_scheduler/scheduler/basis_functions/mask_basis_funcs.py
rubin_scheduler/scheduler/basis_functions/rolling_funcs.py
rubin_scheduler/scheduler/detailers/__init__.py
rubin_scheduler/scheduler/detailers/detailer.py
rubin_scheduler/scheduler/detailers/dither_detailer.py
rubin_scheduler/scheduler/detailers/short_survey.py
rubin_scheduler/scheduler/detailers/vary_exptime.py
rubin_scheduler/scheduler/example/__init__.py
rubin_scheduler/scheduler/example/example_scheduler.py
rubin_scheduler/scheduler/example/simple_examples.py
rubin_scheduler/scheduler/features/__init__.py
rubin_scheduler/scheduler/features/conditions.py
rubin_scheduler/scheduler/features/features.py
rubin_scheduler-4.0.0.dist-info/LICENSE
rubin_scheduler-4.0.0.dist-info/METADATA
rubin_scheduler-4.0.0.dist-info/WHEEL
rubin_scheduler-4.0.0.dist-info/entry_points.txt
rubin_scheduler-4.0.0.dist-info/top_level.txt
rubin_scheduler-4.0.0.dist-info/RECORD
