Metadata-Version: 2.2
Name: rubin-scheduler
Version: 4.0.0
Summary: Scheduling algorithms for Vera C. Rubin Observatory's Legacy Survey of Space and Time (LSST).
License:                     GNU GENERAL PUBLIC LICENSE
Project-URL: documentation, https://rubin-scheduler.lsst.io
Project-URL: repository, https://github.com/lsst/rubin_scheduler
Keywords: rubin,lsst
Classifier: Intended Audience :: Science/Research
Classifier: Operating System :: OS Independent
Classifier: Programming Language :: Python :: 3
Classifier: Programming Language :: Python :: 3.10
Classifier: Programming Language :: Python :: 3.11
Classifier: Topic :: Scientific/Engineering :: Astronomy
License-File: LICENSE
Requires-Dist: numpy
Requires-Dist: matplotlib
Requires-Dist: healpy
Requires-Dist: numexpr
Requires-Dist: scipy<1.14
Requires-Dist: astropy
Requires-Dist: astroplan
Requires-Dist: tables
Requires-Dist: h5py
Requires-Dist: requests
Requires-Dist: shapely
Requires-Dist: tqdm
Requires-Dist: gitpython
Provides-Extra: test
Requires-Dist: pytest; extra == "test"
Requires-Dist: black; extra == "test"
Requires-Dist: ruff; extra == "test"
Requires-Dist: isort; extra == "test"
Requires-Dist: pytest-cov; extra == "test"
Requires-Dist: lsst.resources; extra == "test"
Provides-Extra: dev
Requires-Dist: documenteer[guide]; extra == "dev"
